pipeline_sdk_test52/__init__.py
pipeline_sdk_test52/auth_service.py
pipeline_sdk_test52/inference_pipeline.py
pipeline_sdk_test52/model_inference_dsl_component.py
pipeline_sdk_test52/model_train_dsl_component.py
pipeline_sdk_test52/model_validate_dsl_component.py
pipeline_sdk_test52/pipeline_util.py
pipeline_sdk_test52/run_inference_pipeline.py
pipeline_sdk_test52/run_training_pipeline.py
pipeline_sdk_test52/run_validate_pipeline.py
pipeline_sdk_test52/train_pipeline.py
pipeline_sdk_test52/validate_pipeline.py
pipeline_sdk_test52-1.0.0.dist-info/METADATA
pipeline_sdk_test52-1.0.0.dist-info/WHEEL
pipeline_sdk_test52-1.0.0.dist-info/top_level.txt
pipeline_sdk_test52-1.0.0.dist-info/RECORD
